test_case/__init__.py
util/__init__.py
util/assert_util.py
util/excel_util.py
util/global_var.py
util/json_util.py
util/keyword_function.py
util/log_util.py
util/mongo_util.py
util/mqtt_util.py
util/mysql_util.py
util/preprocess_util.py
util/request_util.py
ciciautoapi-1.0.9.dist-info/METADATA
ciciautoapi-1.0.9.dist-info/WHEEL
ciciautoapi-1.0.9.dist-info/top_level.txt
ciciautoapi-1.0.9.dist-info/RECORD
